kyan/__init__.py
kyan/__main__.py
kyan/configure_audio_devices_ui.py
kyan/import_audio_file_ui.py
kyan/kyan_main.py
kyan/main_ui.py
Kyan-1.1.0.dist-info/LICENSE
Kyan-1.1.0.dist-info/METADATA
Kyan-1.1.0.dist-info/WHEEL
Kyan-1.1.0.dist-info/top_level.txt
Kyan-1.1.0.dist-info/RECORD
