Metadata-Version: 2.1
Name: Kyan
Version: 1.1.0
Summary: A soundboard program written in python
Home-page: https://github.com/DoubleF3lix/Kyan/
License: UNKNOWN
Platform: UNKNOWN
Classifier: Programming Language :: Python :: 3
Classifier: License :: OSI Approved :: GNU Lesser General Public License v3 (LGPLv3)
Classifier: Operating System :: Microsoft :: Windows :: Windows 10
